psychopy_eyelink/__init__.py
psychopy_eyelink/BufferedData/__init__.py
psychopy_eyelink/BufferedData/classic/BufferedData.png
psychopy_eyelink/BufferedData/dark/BufferedData.png
psychopy_eyelink/BufferedData/light/BufferedData.png
psychopy_eyelink/CameraSetup/__init__.py
psychopy_eyelink/CameraSetup/classic/CameraSetup.png
psychopy_eyelink/CameraSetup/dark/CameraSetup.png
psychopy_eyelink/CameraSetup/light/CameraSetup.png
psychopy_eyelink/DriftCheck/__init__.py
psychopy_eyelink/DriftCheck/classic/DriftCheck.png
psychopy_eyelink/DriftCheck/dark/DriftCheck.png
psychopy_eyelink/DriftCheck/light/DriftCheck.png
psychopy_eyelink/GazeTrigger/__init__.py
psychopy_eyelink/GazeTrigger/classic/GazeTrigger.png
psychopy_eyelink/GazeTrigger/dark/GazeTrigger.png
psychopy_eyelink/GazeTrigger/light/GazeTrigger.png
psychopy_eyelink/HostDrawing/__init__.py
psychopy_eyelink/HostDrawing/classic/HostDrawing.png
psychopy_eyelink/HostDrawing/dark/HostDrawing.png
psychopy_eyelink/HostDrawing/light/HostDrawing.png
psychopy_eyelink/InitializeConnection/__init__.py
psychopy_eyelink/InitializeConnection/classic/Initialize.png
psychopy_eyelink/InitializeConnection/dark/Initialize.png
psychopy_eyelink/InitializeConnection/light/Initialize.png
psychopy_eyelink/LatestSample/__init__.py
psychopy_eyelink/LatestSample/classic/LatestSample.png
psychopy_eyelink/LatestSample/dark/LatestSample.png
psychopy_eyelink/LatestSample/light/LatestSample.png
psychopy_eyelink/MarkEvents/__init__.py
psychopy_eyelink/MarkEvents/classic/MarkEvents.png
psychopy_eyelink/MarkEvents/dark/MarkEvents.png
psychopy_eyelink/MarkEvents/light/MarkEvents.png
psychopy_eyelink/StartRecording/__init__.py
psychopy_eyelink/StartRecording/classic/StartRecording.png
psychopy_eyelink/StartRecording/dark/StartRecording.png
psychopy_eyelink/StartRecording/light/StartRecording.png
psychopy_eyelink/StopRecording/__init__.py
psychopy_eyelink/StopRecording/classic/StopRecording.png
psychopy_eyelink/StopRecording/dark/StopRecording.png
psychopy_eyelink-2.1.1179.post3.dist-info/licenses/LICENSE
psychopy_eyelink-2.1.1179.post3.dist-info/METADATA
psychopy_eyelink-2.1.1179.post3.dist-info/WHEEL
psychopy_eyelink-2.1.1179.post3.dist-info/entry_points.txt
psychopy_eyelink-2.1.1179.post3.dist-info/top_level.txt
psychopy_eyelink-2.1.1179.post3.dist-info/RECORD
